[
    {
      "month": "January",
      "sales": 100
    },
    {
      "month": "February",
      "sales": 120
    },
    {
      "month": "March",
      "sales": 150
    },
    {
      "month": "April",
      "sales": 170
    },
    {
      "month": "May",
      "sales": 200
    },
    {
      "month": "June",
      "sales": 220
    },
    {
      "month": "July",
      "sales": 250
    },
    {
      "month": "August",
      "sales": 270
    },
    {
      "month": "September",
      "sales": 300
    },
    {
      "month": "October",
      "sales": 320
    },
    {
      "month": "November",
      "sales": 350
    },
    {
      "month": "December",
      "sales": 370
    }
  ]
  